authorizenet/__init__.py
authorizenet/apicontractsv1.py
authorizenet/apicontrollers.py
authorizenet/apicontrollersbase.py
authorizenet/constants.py
authorizenet/utility.py
authorizenet_pyxb_new-1.1.7.dist-info/LICENSE.txt
authorizenet_pyxb_new-1.1.7.dist-info/METADATA
authorizenet_pyxb_new-1.1.7.dist-info/WHEEL
authorizenet_pyxb_new-1.1.7.dist-info/top_level.txt
authorizenet_pyxb_new-1.1.7.dist-info/RECORD
