Metadata-Version: 2.1
Name: authorizenet-pyxb-new
Version: 1.1.7
Summary: Authorize.Net Python SDK
Home-page: https://github.com/AuthorizeNet/sdk-python
Author: Authorize.Net Developer
Author-email: developer@authorize.net
Maintainer: Max Bridgland
Maintainer-email: me@maxbridgland.com
License: proprietary
Keywords: authorizenet,authorize.net,payment,ecommerce
Classifier: Development Status :: 4 - Beta
Classifier: Intended Audience :: Developers
Classifier: Topic :: Software Development :: Build Tools
Classifier: License :: Other/Proprietary License
Classifier: Programming Language :: Python :: 2.7
Classifier: Programming Language :: Python :: 3.4
License-File: LICENSE.txt
Requires-Dist: pyxb-new (==1.2.8)
Requires-Dist: lxml (==4.*)
Requires-Dist: requests (==2.*)
